zenity_judo/__init__.py
zenity_judo/__main__.py
zenity_judo-1.0.3.dist-info/LICENSE
zenity_judo-1.0.3.dist-info/WHEEL
zenity_judo-1.0.3.dist-info/METADATA
zenity_judo-1.0.3.dist-info/RECORD
