Metadata-Version: 2.1
Name: zenity_judo
Version: 1.0.3
Summary: Python wrapper for zenity.
Author-email: Leon Dionne <ldionne@dridesign.sh.cn>
Classifier: License :: OSI Approved :: GNU General Public License v3 or later (GPLv3+)
Classifier: Development Status :: 3 - Alpha
Classifier: Environment :: X11 Applications :: GTK
Classifier: Operating System :: POSIX :: Linux
Classifier: Programming Language :: Python :: 3
Classifier: Topic :: Desktop Environment
Classifier: Topic :: Desktop Environment :: Gnome
Project-URL: Home, https://github.com/Zen-Master-SoSo/zenity_judo
